sqldbwrpr/__init__.py
sqldbwrpr/sqldbwrpr.py
sqldbwrpr-5.0.1.dist-info/METADATA
sqldbwrpr-5.0.1.dist-info/WHEEL
sqldbwrpr-5.0.1.dist-info/licenses/LICENSE.txt
sqldbwrpr-5.0.1.dist-info/RECORD
