Metadata-Version: 2.4
Name: SQLDbWrpr
Version: 5.0.1
Summary: Wrapper for importing CSV and Text files into MySQL and Postgress
License-Expression: MIT
License-File: LICENSE.txt
Author: Hendrik du Toit
Author-email: hendrik@brightedge.co.za
Maintainer: Hendrik du Toit
Maintainer-email: hendrikdt@citiqprepaid.co.za
Requires-Python: >=3.10
Classifier: Development Status :: 4 - Beta
Classifier: Intended Audience :: Developers
Classifier: Intended Audience :: Information Technology
Classifier: Topic :: Software Development
Classifier: Topic :: Text Processing
Classifier: Topic :: Utilities
Classifier: License :: OSI Approved :: MIT License
Classifier: Programming Language :: Python :: 3.10
Classifier: Programming Language :: Python :: 3.11
Classifier: Programming Language :: Python :: 3.12
Classifier: Programming Language :: Python :: 3.13
Requires-Dist: csvwrpr (>=1.16.1,<2.0.0)
Requires-Dist: fixdate (>=2.1.0,<3.0.0)
Requires-Dist: mysql-connector (>=2.2.9,<3.0.0)
Requires-Dist: pydantic-settings (>=2.12.0,<3.0.0)
Requires-Dist: pyodbc (>=5.3.0,<6.0.0)
Project-URL: Homepage, https://github.com/BrightEdgeeServices/SqlDbWrpr
Project-URL: Issues, https://github.com/BrightEdgeeServices/SqlDbWrpr/issues
Project-URL: Repository, https://github.com/BrightEdgeeServices/SqlDbWrpr.git
Project-URL: changelog, https://github.com/BrightEdgeeServices/SqlDbWrpr/releases
